twitchez/__init__.py
twitchez/__main__.py
twitchez/auth.py
twitchez/bmark.py
twitchez/clip.py
twitchez/command.py
twitchez/conf.py
twitchez/data.py
twitchez/fs.py
twitchez/hints.py
twitchez/init.py
twitchez/iselect.py
twitchez/keys.py
twitchez/keys_help.py
twitchez/notify.py
twitchez/open_chat.py
twitchez/open_cmd.py
twitchez/paged.py
twitchez/pages.py
twitchez/render.py
twitchez/search.py
twitchez/tabs.py
twitchez/thumbnails.py
twitchez/utils.py
twitchez/config/blank.jpg
twitchez/config/default.conf
twitchez/config/defkeys.conf
twitchez-0.1.0.dist-info/LICENSE
twitchez-0.1.0.dist-info/METADATA
twitchez-0.1.0.dist-info/WHEEL
twitchez-0.1.0.dist-info/entry_points.txt
twitchez-0.1.0.dist-info/top_level.txt
twitchez-0.1.0.dist-info/RECORD
