Metadata-Version: 2.1
Name: twitchez
Version: 0.1.0
Summary: twitchez - TUI client for twitch.tv with thumbnails support that works right in your terminal
Home-page: https://github.com/WANDEX/twitchez
Author: WANDEX
License: GPLv3
Project-URL: Bug Reports, https://github.com/WANDEX/twitchez/issues
Project-URL: Source, https://github.com/WANDEX/twitchez
Keywords: twitch TUI terminal curses ui client thumbnail image twitch.tv
Classifier: License :: OSI Approved :: GNU General Public License v3 (GPLv3)
Classifier: Programming Language :: Python :: 3
Classifier: Environment :: Console :: Curses
Classifier: Operating System :: POSIX
Classifier: Operating System :: Unix
Classifier: Development Status :: 4 - Beta
Requires-Python: >=3.6
License-File: LICENSE
Requires-Dist: aiohttp
Requires-Dist: requests
Provides-Extra: thumbnails
Requires-Dist: ueberzugpp; extra == "thumbnails"
Requires-Dist: ueberzug; extra == "thumbnails"
